device2sms_sdk/__init__.py
device2sms_sdk/client.py
device2sms_sdk/py.typed
device2sms_sdk-0.1.1.dist-info/licenses/LICENSE
device2sms_sdk-0.1.1.dist-info/METADATA
device2sms_sdk-0.1.1.dist-info/WHEEL
device2sms_sdk-0.1.1.dist-info/top_level.txt
device2sms_sdk-0.1.1.dist-info/RECORD
