Metadata-Version: 2.4
Name: device2sms-sdk
Version: 0.1.1
Summary: Device2SMS Python SDK (E2EE via Google Tink)
Author-email: The Codefather <support@thecodefather.ie>
License-Expression: MIT
Project-URL: Homepage, https://device2sms.ie
Project-URL: Documentation, https://docs.device2sms.ie
Keywords: sms,e2ee,tink,device2sms
Classifier: Programming Language :: Python :: 3
Classifier: Programming Language :: Python :: 3 :: Only
Classifier: Programming Language :: Python :: 3.11
Classifier: Programming Language :: Python :: 3.12
Classifier: Programming Language :: Python :: 3.13
Requires-Python: >=3.11
License-File: LICENSE
Requires-Dist: requests>=2.31.0
Requires-Dist: tink>=1.9.0
Dynamic: license-file
